gaurav_test0_sdk/__init__.py
gaurav_test0_sdk/api_client.py
gaurav_test0_sdk/api_response.py
gaurav_test0_sdk/configuration.py
gaurav_test0_sdk/exceptions.py
gaurav_test0_sdk/py.typed
gaurav_test0_sdk/rest.py
gaurav_test0_sdk/api/__init__.py
gaurav_test0_sdk/api/pet_api.py
gaurav_test0_sdk/api/store_api.py
gaurav_test0_sdk/api/user_api.py
gaurav_test0_sdk/models/__init__.py
gaurav_test0_sdk/models/address.py
gaurav_test0_sdk/models/api_response.py
gaurav_test0_sdk/models/category.py
gaurav_test0_sdk/models/customer.py
gaurav_test0_sdk/models/order.py
gaurav_test0_sdk/models/pet.py
gaurav_test0_sdk/models/tag.py
gaurav_test0_sdk/models/user.py
gaurav_test0_sdk-1.0.0.dist-info/METADATA
gaurav_test0_sdk-1.0.0.dist-info/WHEEL
gaurav_test0_sdk-1.0.0.dist-info/top_level.txt
gaurav_test0_sdk-1.0.0.dist-info/RECORD
